{
  "consumer": {
    "name": "BureauData"
  },
  "provider": {
    "name": "BureauDataProvider"
  },
  "interactions": [
    {
      "description": "BureauData should have a get rest for BureauData",
      "providerState": "default",
      "request": {
        "method": "GET",
        "path": "/v1/cradata",
        "query": "accountSeq=accountSeq&applicationRef=applicationRef&brandRef=brandRef&clientRef=clientRef&employmentSeq=employmentSeq&vbAccountSeq=vbAccountSeq&vbAccountType=vbAccountType"
      },
      "response": {
        "status": 200,
        "headers": {
        },
        "body": {
          "reducedPayment": "N",
          "reducedPaymentAmount": 123,
          "creditInsurance": "N",
          "queryMade": "N",
          "arrearsReplay": "N",
          "performanceLevel": "high"
        }
      }
    },
    {
      "description": "BureauData should have a get fetcher for BureauData",
      "providerState": "default",
      "request": {
        "method": "GET",
        "path": "/v1/cradata",
        "query": "accountSeq=accountSeq&applicationRef=applicationRef&brandRef=brandRef&clientRef=clientRef&employmentSeq=employmentSeq&vbAccountSeq=vbAccountSeq&vbAccountType=vbAccountType"
      },
      "response": {
        "status": 200,
        "headers": {
        },
        "body": {
          "reducedPayment": "N",
          "reducedPaymentAmount": 123,
          "creditInsurance": "N",
          "queryMade": "N",
          "arrearsReplay": "N",
          "performanceLevel": "high"
        }
      }
    },
    {
      "description": "a rest for BureauData bureauData get",
      "providerState": "default",
      "request": {
        "method": "GET",
        "path": "/v1/cradata",
        "query": "accountSeq=accountSeq&applicationRef=applicationRef&brandRef=brandRef&clientRef=clientRef&employmentSeq=employmentSeq&vbAccountSeq=vbAccountSeq&vbAccountType=vbAccountType"
      },
      "response": {
        "status": 200,
        "headers": {
        }
      }
    }
  ],
  "metadata": {
    "pactSpecification": {
      "version": "2.0.0"
    }
  }
}